{
   "SelectionNodeList":[
      {
         "Id":"94",
         "Title":"Stakeholder requirement title text #1"
      },
      {
         "Id":"95",
         "Title":"Stakeholder requirement title text #2"
      },
      {
         "Id":"96",
         "Title":"Stakeholder requirement title text #3"
      },
      {
         "Id":"98",
         "Title":"Technical requirement title text #1"
      },
      {
         "Id":"99",
         "Title":"Technical requirement title text #2"
      },
      {
         "Id":"100",
         "Title":"Technical requirement title text #3"
      },
      {
         "Id":"101",
         "Title":"Technical requirement title text #4"
      },
      {
         "Id":"102",
         "Title":"Technical requirement title text #5"
      },
      {
         "Id":"103",
         "Title":"Technical requirement title text #6"
      },
      {
         "Id":"104",
         "Title":"Technical requirement title text #7"
      },
      {
         "Id":"105",
         "Title":"Technical requirement title text #8"
      },
      {
         "Id":"106",
         "Title":"Technical requirement title text #9"
      },
      {
         "Id":"107",
         "Title":"Technical requirement title text #10"
      },
      {
         "Id":"108",
         "Title":"Technical requirement title text #11"
      },
      {
         "Id":"109",
         "Title":"Technical requirement title text #12"
      }
   ]
}
